{
  "breadcrumbs.enabled": false,
  "cucumberautocomplete.skipDocStringsFormat": true,
  "diffEditor.ignoreTrimWhitespace": false,
  "diffEditor.renderIndicators": false,
  "editor.accessibilitySupport": "off",
  "editor.autoClosingBrackets": "beforeWhitespace",
  "editor.autoClosingQuotes": "beforeWhitespace",
  "editor.colorDecorators": false,
  "editor.dragAndDrop": false,
  "editor.emptySelectionClipboard": false,
  "editor.folding": false,
  "editor.formatOnPaste": true,
  "editor.formatOnSave": true,
  "editor.formatOnType": true,
  "editor.highlightActiveIndentGuide": false,
  "editor.hover.sticky": false,
  "editor.largeFileOptimizations": false,
  "editor.minimap.enabled": false,
  "editor.quickSuggestions": {
    "comments": true,
    "other": true,
    "strings": true
  },
  "editor.renderControlCharacters": false,
  "editor.roundedSelection": false,
  "editor.scrollBeyondLastLine": false,
  "editor.selectionHighlight": true,
  "editor.occurrencesHighlight": true,
  "editor.tabSize": 2,
  "explorer.confirmDelete": false,
  "explorer.confirmDragAndDrop": false,
  "files.hotExit": "off",
  "files.insertFinalNewline": true,
  "files.trimFinalNewlines": true,
  "files.trimTrailingWhitespace": true,
  "git.ignoreMissingGitWarning": false,
  "git.promptToSaveFilesBeforeCommit": true,
  "javascript.updateImportsOnFileMove.enabled": "always",
  "npm.packageManager": "yarn",
  "scm.diffDecorations": "none",
  "scrolloff.alwaysCenter": true,
  "search.smartCase": true,
  "terminal.integrated.shell.windows": "C:\\Program Files\\Git\\bin\\bash.exe",
  "tslint.alwaysShowRuleFailuresAsWarnings": true,
  "tslint.packageManager": "yarn",
  "tslint.run": "onSave",
  "typescript.updateImportsOnFileMove.enabled": "always",
  "vim.debug.loggingLevel": "debug",
  "vim.handleKeys": {
    "<C-a>": false,
    "<C-b>": false,
    "<C-c>": false,
    "<C-t>": false
  },
  "vim.hlsearch": true,
  "vim.leader": "<space>",
  "vim.normalModeKeyBindingsNonRecursive": [
    {
      "after": ["i", "<space>", "<esc>"],
      "before": ["<leader>", "<leader>"]
    },
    {
      "after": ["o", "<esc>", "k"],
      "before": ["<enter>"]
    },
    {
      "after": ["l"],
      "before": ["s"]
    },
    {
      "after": ["s"],
      "before": ["l"]
    },
    {
      "before": ["<leader>", "/"],
      "commands": [":nohl"]
    },
    {
      "before": [":"],
      "commands": ["workbench.action.showCommands"]
    },
    {
      "before": ["j"],
      "after": ["g", "j"]
    },
    {
      "before": ["k"],
      "after": ["g", "k"]
    }
  ],
  "vim.statusBarColorControl": false,
  "window.autoDetectHighContrast": false,
  "window.enableMenuBarMnemonics": false,
  "window.title": "${rootName}${separator}${activeEditorMedium}",
  "window.zoomLevel": 0,
  "workbench.activityBar.visible": false,
  "workbench.colorTheme": "Default Light+",
  "workbench.colorCustomizations": {
    "[Default Light+]": {
      "editor.lineHighlightBackground": "#f4f4ff"
    }
  },
  "workbench.editor.revealIfOpen": true,
  "workbench.quickOpen.closeOnFocusLost": false,
  "workbench.statusBar.feedback.visible": false,
  "[markdown]": {
    "editor.occurrencesHighlight": false,
    "editor.selectionHighlight": false
  }
}
